se3kit/__init__.py
se3kit/degrees.py
se3kit/hpoint.py
se3kit/ros_compat.py
se3kit/rotation.py
se3kit/transformation.py
se3kit/translation.py
se3kit/utils.py
se3kit/calibration/__init__.py
se3kit/calibration/eye_in_hand_calibration.py
se3kit/calibration/p2p_registration.py
se3kit/calibration/pivot_calibration.py
se3kit-1.0.5.dist-info/licenses/LICENSE
se3kit-1.0.5.dist-info/METADATA
se3kit-1.0.5.dist-info/WHEEL
se3kit-1.0.5.dist-info/top_level.txt
se3kit-1.0.5.dist-info/RECORD
