Metadata-Version: 2.4
Name: se3kit
Version: 1.0.5
Summary: 3D rigid-body transformations and rotations
Author-email: Daniyal Maroufi <daniyalmaroufi8@gmail.com>, Omid Rezayof <omid.rezayof@utexas.edu>
License: Apache-2.0
Project-URL: Homepage, https://pypi.org/project/se3kit/
Project-URL: Documentation, https://daniyalmaroufi.github.io/se3kit/
Project-URL: Repository, https://github.com/daniyalmaroufi/se3kit
Keywords: se3,robotics,rigid-body transformations,se3kit
Platform: any
Classifier: Development Status :: 4 - Beta
Classifier: Intended Audience :: Developers
Classifier: Natural Language :: English
Classifier: Programming Language :: Python :: 3
Classifier: Programming Language :: Python :: 3.8
Classifier: Programming Language :: Python :: 3.9
Classifier: Programming Language :: Python :: 3.11
Classifier: Programming Language :: Python :: 3.12
Classifier: License :: OSI Approved :: Apache Software License
Classifier: Topic :: Scientific/Engineering
Requires-Python: >=3.8
License-File: LICENSE
Requires-Dist: numpy
Requires-Dist: numpy-quaternion
Provides-Extra: dev
Requires-Dist: black; extra == "dev"
Requires-Dist: pre-commit; extra == "dev"
Requires-Dist: ruff; extra == "dev"
Requires-Dist: isort; extra == "dev"
Requires-Dist: sphinx; extra == "dev"
Requires-Dist: sphinx_rtd_theme; extra == "dev"
Provides-Extra: setup
Requires-Dist: build; extra == "setup"
Requires-Dist: setuptools; extra == "setup"
Requires-Dist: twine; extra == "setup"
Dynamic: license-file
